{
	"inputs" : 
	[
		{
			"path" : "CMakeLists.txt"
		},
		{
			"isGenerated" : true,
			"path" : "build/CMakeFiles/3.17.0/CMakeSystem.cmake"
		},
		{
			"isCMake" : true,
			"isExternal" : true,
			"path" : "C:/Program Files/CMake/share/cmake-3.17/Modules/CMakeSystemSpecificInitialize.cmake"
		},
		{
			"isGenerated" : true,
			"path" : "build/CMakeFiles/3.17.0/CMakeCCompiler.cmake"
		},
		{
			"isCMake" : true,
			"isExternal" : true,
			"path" : "C:/Program Files/CMake/share/cmake-3.17/Modules/CMakeSystemSpecificInformation.cmake"
		},
		{
			"isCMake" : true,
			"isExternal" : true,
			"path" : "C:/Program Files/CMake/share/cmake-3.17/Modules/CMakeGenericSystem.cmake"
		},
		{
			"isCMake" : true,
			"isExternal" : true,
			"path" : "C:/Program Files/CMake/share/cmake-3.17/Modules/CMakeInitializeConfigs.cmake"
		},
		{
			"isCMake" : true,
			"isExternal" : true,
			"path" : "C:/Program Files/CMake/share/cmake-3.17/Modules/Platform/Windows.cmake"
		},
		{
			"isCMake" : true,
			"isExternal" : true,
			"path" : "C:/Program Files/CMake/share/cmake-3.17/Modules/Platform/WindowsPaths.cmake"
		},
		{
			"isCMake" : true,
			"isExternal" : true,
			"path" : "C:/Program Files/CMake/share/cmake-3.17/Modules/CMakeCInformation.cmake"
		},
		{
			"isCMake" : true,
			"isExternal" : true,
			"path" : "C:/Program Files/CMake/share/cmake-3.17/Modules/CMakeLanguageInformation.cmake"
		},
		{
			"isCMake" : true,
			"isExternal" : true,
			"path" : "C:/Program Files/CMake/share/cmake-3.17/Modules/Compiler/GNU-C.cmake"
		},
		{
			"isCMake" : true,
			"isExternal" : true,
			"path" : "C:/Program Files/CMake/share/cmake-3.17/Modules/Compiler/GNU.cmake"
		},
		{
			"isCMake" : true,
			"isExternal" : true,
			"path" : "C:/Program Files/CMake/share/cmake-3.17/Modules/Compiler/CMakeCommonCompilerMacros.cmake"
		},
		{
			"isCMake" : true,
			"isExternal" : true,
			"path" : "C:/Program Files/CMake/share/cmake-3.17/Modules/Internal/CMakeCheckCompilerFlag.cmake"
		},
		{
			"isCMake" : true,
			"isExternal" : true,
			"path" : "C:/Program Files/CMake/share/cmake-3.17/Modules/CMakeCheckCompilerFlagCommonPatterns.cmake"
		},
		{
			"isCMake" : true,
			"isExternal" : true,
			"path" : "C:/Program Files/CMake/share/cmake-3.17/Modules/Platform/Windows-GNU-C.cmake"
		},
		{
			"isCMake" : true,
			"isExternal" : true,
			"path" : "C:/Program Files/CMake/share/cmake-3.17/Modules/Platform/Windows-GNU.cmake"
		},
		{
			"isGenerated" : true,
			"path" : "build/CMakeFiles/3.17.0/CMakeRCCompiler.cmake"
		},
		{
			"isCMake" : true,
			"isExternal" : true,
			"path" : "C:/Program Files/CMake/share/cmake-3.17/Modules/CMakeRCInformation.cmake"
		},
		{
			"isCMake" : true,
			"isExternal" : true,
			"path" : "C:/Program Files/CMake/share/cmake-3.17/Modules/Platform/Windows-windres.cmake"
		},
		{
			"isCMake" : true,
			"isExternal" : true,
			"path" : "C:/Program Files/CMake/share/cmake-3.17/Modules/Platform/Windows-GNU-C-ABI.cmake"
		},
		{
			"isCMake" : true,
			"isExternal" : true,
			"path" : "C:/Program Files/CMake/share/cmake-3.17/Modules/CMakeCommonLanguageInclude.cmake"
		},
		{
			"path" : "libs/raylib/CMakeLists.txt"
		},
		{
			"path" : "libs/raylib/cmake/AddIfFlagCompiles.cmake"
		},
		{
			"isCMake" : true,
			"isExternal" : true,
			"path" : "C:/Program Files/CMake/share/cmake-3.17/Modules/CheckCCompilerFlag.cmake"
		},
		{
			"isCMake" : true,
			"isExternal" : true,
			"path" : "C:/Program Files/CMake/share/cmake-3.17/Modules/CheckCSourceCompiles.cmake"
		},
		{
			"isCMake" : true,
			"isExternal" : true,
			"path" : "C:/Program Files/CMake/share/cmake-3.17/Modules/CMakeCheckCompilerFlagCommonPatterns.cmake"
		},
		{
			"path" : "libs/raylib/cmake/CheckFileSystemSymlinkSupport.cmake"
		},
		{
			"path" : "libs/raylib/src/CMakeLists.txt"
		},
		{
			"isCMake" : true,
			"isExternal" : true,
			"path" : "C:/Program Files/CMake/share/cmake-3.17/Modules/GNUInstallDirs.cmake"
		},
		{
			"path" : "libs/raylib/src/CMakeOptions.txt"
		},
		{
			"isCMake" : true,
			"isExternal" : true,
			"path" : "C:/Program Files/CMake/share/cmake-3.17/Modules/CMakeDependentOption.cmake"
		},
		{
			"path" : "libs/raylib/cmake/EnumOption.cmake"
		},
		{
			"path" : "libs/raylib/cmake/BuildType.cmake"
		},
		{
			"path" : "libs/raylib/src/config.h.in"
		},
		{
			"path" : "libs/raylib/cmake/LibraryPathToLinkerFlags.cmake"
		},
		{
			"path" : "libs/raylib/raylib.pc.in"
		},
		{
			"path" : "libs/raylib/cmake/raylib-config-version.cmake"
		},
		{
			"path" : "libs/raylib/cmake/PopulateConfigVariablesLocally.cmake"
		},
		{
			"isCMake" : true,
			"isExternal" : true,
			"path" : "C:/Program Files/CMake/share/cmake-3.17/Modules/CPack.cmake"
		},
		{
			"isCMake" : true,
			"isExternal" : true,
			"path" : "C:/Program Files/CMake/share/cmake-3.17/Modules/CPackComponent.cmake"
		},
		{
			"isExternal" : true,
			"path" : "C:/Program Files/CMake/share/cmake-3.17/Templates/CPackConfig.cmake.in"
		},
		{
			"isExternal" : true,
			"path" : "C:/Program Files/CMake/share/cmake-3.17/Templates/CPackConfig.cmake.in"
		},
		{
			"path" : "libs/raylib/src/external/glfw/CMakeLists.txt"
		},
		{
			"isCMake" : true,
			"isExternal" : true,
			"path" : "C:/Program Files/CMake/share/cmake-3.17/Modules/GNUInstallDirs.cmake"
		},
		{
			"isCMake" : true,
			"isExternal" : true,
			"path" : "C:/Program Files/CMake/share/cmake-3.17/Modules/CMakeDependentOption.cmake"
		},
		{
			"isCMake" : true,
			"isExternal" : true,
			"path" : "C:/Program Files/CMake/share/cmake-3.17/Modules/FindThreads.cmake"
		},
		{
			"isCMake" : true,
			"isExternal" : true,
			"path" : "C:/Program Files/CMake/share/cmake-3.17/Modules/CheckLibraryExists.cmake"
		},
		{
			"isCMake" : true,
			"isExternal" : true,
			"path" : "C:/Program Files/CMake/share/cmake-3.17/Modules/CheckIncludeFile.cmake"
		},
		{
			"isCMake" : true,
			"isExternal" : true,
			"path" : "C:/Program Files/CMake/share/cmake-3.17/Modules/CheckCSourceCompiles.cmake"
		},
		{
			"isCMake" : true,
			"isExternal" : true,
			"path" : "C:/Program Files/CMake/share/cmake-3.17/Modules/FindPackageHandleStandardArgs.cmake"
		},
		{
			"isCMake" : true,
			"isExternal" : true,
			"path" : "C:/Program Files/CMake/share/cmake-3.17/Modules/FindPackageMessage.cmake"
		},
		{
			"isCMake" : true,
			"isExternal" : true,
			"path" : "C:/Program Files/CMake/share/cmake-3.17/Modules/CheckIncludeFile.cmake"
		},
		{
			"isCMake" : true,
			"isExternal" : true,
			"path" : "C:/Program Files/CMake/share/cmake-3.17/Modules/CheckCCompilerFlag.cmake"
		},
		{
			"isCMake" : true,
			"isExternal" : true,
			"path" : "C:/Program Files/CMake/share/cmake-3.17/Modules/CMakePackageConfigHelpers.cmake"
		},
		{
			"isCMake" : true,
			"isExternal" : true,
			"path" : "C:/Program Files/CMake/share/cmake-3.17/Modules/WriteBasicConfigVersionFile.cmake"
		},
		{
			"path" : "libs/raylib/src/external/glfw/src/glfw3Config.cmake.in"
		},
		{
			"isCMake" : true,
			"isExternal" : true,
			"path" : "C:/Program Files/CMake/share/cmake-3.17/Modules/BasicConfigVersion-SameMajorVersion.cmake.in"
		},
		{
			"path" : "libs/raylib/src/external/glfw/src/glfw_config.h.in"
		},
		{
			"path" : "libs/raylib/src/external/glfw/src/glfw3.pc.in"
		},
		{
			"path" : "libs/raylib/src/external/glfw/src/CMakeLists.txt"
		}
	],
	"kind" : "cmakeFiles",
	"paths" : 
	{
		"build" : "C:/Users/marti/Documents/StringBeat/build",
		"source" : "C:/Users/marti/Documents/StringBeat"
	},
	"version" : 
	{
		"major" : 1,
		"minor" : 0
	}
}
